{
"meta":{"test_sets":[],"test_metrics":[],"learn_metrics":[{"best_value":"Min","name":"RMSE"}],"launch_mode":"Train","parameters":"","iteration_count":500,"learn_sets":["learn"],"name":"experiment"},
"iterations":[
{"learn":[258682.5656],"iteration":0,"passed_time":0.7792757185,"remaining_time":388.8585835},
{"learn":[250099.51],"iteration":1,"passed_time":1.283640173,"remaining_time":319.6264032},
{"learn":[241902.8866],"iteration":2,"passed_time":1.969309158,"remaining_time":326.2488838},
{"learn":[235087.6272],"iteration":3,"passed_time":2.440691544,"remaining_time":302.6457515},
{"learn":[229434.7221],"iteration":4,"passed_time":2.863233268,"remaining_time":283.4600936},
{"learn":[224679.9205],"iteration":5,"passed_time":3.152528672,"remaining_time":259.558194},
{"learn":[220750.0149],"iteration":6,"passed_time":3.427542846,"remaining_time":241.3969461},
{"learn":[217509.1379],"iteration":7,"passed_time":4.08722176,"remaining_time":251.3641382},
{"learn":[214790.5563],"iteration":8,"passed_time":4.490598381,"remaining_time":244.9870894},
{"learn":[211355.4619],"iteration":9,"passed_time":4.987435619,"remaining_time":244.3843453},
{"learn":[208518.5003],"iteration":10,"passed_time":5.285852018,"remaining_time":234.9801488},
{"learn":[206251.5949],"iteration":11,"passed_time":5.5979316,"remaining_time":227.6492184},
{"learn":[204397.8518],"iteration":12,"passed_time":5.896978754,"remaining_time":220.9098964},
{"learn":[202873.6934],"iteration":13,"passed_time":6.156452524,"remaining_time":213.7168519},
{"learn":[201814.5355],"iteration":14,"passed_time":6.713130058,"remaining_time":217.0578719},
{"learn":[198905.7733],"iteration":15,"passed_time":7.389749792,"remaining_time":223.5399312},
{"learn":[196502.2219],"iteration":16,"passed_time":7.998092777,"remaining_time":227.2399301},
{"learn":[194523.5531],"iteration":17,"passed_time":8.388133862,"remaining_time":224.6155845},
{"learn":[193695.8922],"iteration":18,"passed_time":8.717205845,"remaining_time":220.682948},
{"learn":[191892.067],"iteration":19,"passed_time":9.007626139,"remaining_time":216.1830273},
{"learn":[190402.4794],"iteration":20,"passed_time":9.301587471,"remaining_time":212.1647809},
{"learn":[189211.0137],"iteration":21,"passed_time":9.652023092,"remaining_time":209.7121381},
{"learn":[188290.8911],"iteration":22,"passed_time":10.22553616,"remaining_time":212.0687282},
{"learn":[187443.8068],"iteration":23,"passed_time":10.63387069,"remaining_time":210.9051021},
{"learn":[186772.7895],"iteration":24,"passed_time":10.91331898,"remaining_time":207.3530606},
{"learn":[186222.9204],"iteration":25,"passed_time":11.17307556,"remaining_time":203.6937622},
{"learn":[185769.771],"iteration":26,"passed_time":11.45286199,"remaining_time":200.6371749},
{"learn":[185380.9105],"iteration":27,"passed_time":11.85764949,"remaining_time":199.8860914},
{"learn":[185030.2089],"iteration":28,"passed_time":12.15244669,"remaining_time":197.3724962},
{"learn":[184786.7769],"iteration":29,"passed_time":12.44173563,"remaining_time":194.9205249},
{"learn":[184494.0255],"iteration":30,"passed_time":12.70928963,"remaining_time":192.2792528},
{"learn":[184248.1771],"iteration":31,"passed_time":13.34084277,"remaining_time":195.1098255},
{"learn":[184007.2655],"iteration":32,"passed_time":13.68235255,"remaining_time":193.6260194},
{"learn":[183927.3351],"iteration":33,"passed_time":14.10972673,"remaining_time":193.3862546},
{"learn":[183796.4342],"iteration":34,"passed_time":14.52533208,"remaining_time":192.9794119},
{"learn":[183694.0248],"iteration":35,"passed_time":15.11341069,"remaining_time":194.7950712},
{"learn":[183633.0866],"iteration":36,"passed_time":15.45577026,"remaining_time":193.40599},
{"learn":[183553.9433],"iteration":37,"passed_time":16.07622314,"remaining_time":195.4530287},
{"learn":[183465.0594],"iteration":38,"passed_time":16.46720955,"remaining_time":194.6508615},
{"learn":[183393.4472],"iteration":39,"passed_time":16.74967573,"remaining_time":192.6212709},
{"learn":[183317.7564],"iteration":40,"passed_time":17.23953651,"remaining_time":192.9987136},
{"learn":[183206.4379],"iteration":41,"passed_time":17.54407325,"remaining_time":191.3139417},
{"learn":[183140.8832],"iteration":42,"passed_time":17.86962811,"remaining_time":189.9167453},
{"learn":[183083.8544],"iteration":43,"passed_time":18.34494206,"remaining_time":190.1203086},
{"learn":[183055.7715],"iteration":44,"passed_time":18.82170862,"remaining_time":190.3083872},
{"learn":[183018.4662],"iteration":45,"passed_time":19.22757222,"remaining_time":189.767778},
{"learn":[182985.8683],"iteration":46,"passed_time":19.7496854,"remaining_time":190.3533508},
{"learn":[182793.6773],"iteration":47,"passed_time":20.53210114,"remaining_time":193.3439524},
{"learn":[182756.3571],"iteration":48,"passed_time":20.94242735,"remaining_time":192.7558109},
{"learn":[182738.3941],"iteration":49,"passed_time":21.35505125,"remaining_time":192.1954612},
{"learn":[182723.169],"iteration":50,"passed_time":21.86844604,"remaining_time":192.5280837},
{"learn":[182707.3327],"iteration":51,"passed_time":22.35945671,"remaining_time":192.6353193},
{"learn":[182664.5297],"iteration":52,"passed_time":22.8354669,"remaining_time":192.5934661},
{"learn":[182515.6079],"iteration":53,"passed_time":23.13779032,"remaining_time":191.1010089},
{"learn":[182285.2823],"iteration":54,"passed_time":23.64342907,"remaining_time":191.2968352},
{"learn":[182092.7808],"iteration":55,"passed_time":23.98986118,"remaining_time":190.2053279},
{"learn":[182075.3273],"iteration":56,"passed_time":24.53678463,"remaining_time":190.6981683},
{"learn":[181955.5372],"iteration":57,"passed_time":24.85221418,"remaining_time":189.3910115},
{"learn":[181786.1938],"iteration":58,"passed_time":25.51082878,"remaining_time":190.6826355},
{"learn":[181659.0311],"iteration":59,"passed_time":25.93818509,"remaining_time":190.2133573},
{"learn":[181646.2427],"iteration":60,"passed_time":26.39885499,"remaining_time":189.9852023},
{"learn":[181626.8472],"iteration":61,"passed_time":26.83533847,"remaining_time":189.5786814},
{"learn":[181459.0763],"iteration":62,"passed_time":27.47947302,"remaining_time":190.6115827},
{"learn":[181434.2712],"iteration":63,"passed_time":27.95300869,"remaining_time":190.4298717},
{"learn":[181408.0243],"iteration":64,"passed_time":28.41872271,"remaining_time":190.1868366},
{"learn":[181397.1829],"iteration":65,"passed_time":28.83817675,"remaining_time":189.6328592},
{"learn":[181386.651],"iteration":66,"passed_time":29.35287508,"remaining_time":189.6984315},
{"learn":[181244.5496],"iteration":67,"passed_time":29.89196183,"remaining_time":189.9018752},
{"learn":[181235.299],"iteration":68,"passed_time":30.20642002,"remaining_time":188.6806816},
{"learn":[181106.0106],"iteration":69,"passed_time":30.75890581,"remaining_time":188.9475643},
{"learn":[181019.3531],"iteration":70,"passed_time":31.11391536,"remaining_time":187.9981647},
{"learn":[181010.9764],"iteration":71,"passed_time":31.39002085,"remaining_time":186.596235},
{"learn":[180915.8931],"iteration":72,"passed_time":31.76142726,"remaining_time":185.782595},
{"learn":[180817.193],"iteration":73,"passed_time":32.21881115,"remaining_time":185.4758588},
{"learn":[180809.677],"iteration":74,"passed_time":32.48622123,"remaining_time":184.088587},
{"learn":[180802.8227],"iteration":75,"passed_time":33.02574438,"remaining_time":184.2488897},
{"learn":[180796.2656],"iteration":76,"passed_time":33.65133829,"remaining_time":184.8638454},
{"learn":[180790.0652],"iteration":77,"passed_time":34.15075129,"remaining_time":184.7643211},
{"learn":[180708.102],"iteration":78,"passed_time":34.48998262,"remaining_time":183.8010466},
{"learn":[180652.9152],"iteration":79,"passed_time":35.09411249,"remaining_time":184.2440905},
{"learn":[180620.3731],"iteration":80,"passed_time":35.48320634,"remaining_time":183.5489315},
{"learn":[180599.0462],"iteration":81,"passed_time":35.88706018,"remaining_time":182.9364775},
{"learn":[180553.3528],"iteration":82,"passed_time":36.46637119,"remaining_time":183.2105637},
{"learn":[180478.5141],"iteration":83,"passed_time":36.83545957,"remaining_time":182.4232284},
{"learn":[180466.2489],"iteration":84,"passed_time":37.38367324,"remaining_time":182.520287},
{"learn":[180422.8289],"iteration":85,"passed_time":38.03597901,"remaining_time":183.1034338},
{"learn":[180408.1104],"iteration":86,"passed_time":38.45944205,"remaining_time":182.5718341},
{"learn":[180390.1185],"iteration":87,"passed_time":38.8682778,"remaining_time":181.9742097},
{"learn":[180337.0718],"iteration":88,"passed_time":39.39256369,"remaining_time":181.9139739},
{"learn":[180306.6364],"iteration":89,"passed_time":39.90474201,"remaining_time":181.7882692},
{"learn":[180295.2746],"iteration":90,"passed_time":40.4120155,"remaining_time":181.6320257},
{"learn":[180290.5994],"iteration":91,"passed_time":41.02949944,"remaining_time":181.9569106},
{"learn":[180286.0864],"iteration":92,"passed_time":41.49661671,"remaining_time":181.6034731},
{"learn":[180237.7465],"iteration":93,"passed_time":42.08443388,"remaining_time":181.7689378},
{"learn":[180194.4575],"iteration":94,"passed_time":42.44840469,"remaining_time":180.9642516},
{"learn":[180142.2444],"iteration":95,"passed_time":43.25619533,"remaining_time":182.0364887},
{"learn":[180127.5127],"iteration":96,"passed_time":43.72708495,"remaining_time":181.6702602},
{"learn":[180123.5897],"iteration":97,"passed_time":44.05427975,"remaining_time":180.7124537},
{"learn":[180098.0861],"iteration":98,"passed_time":44.67227075,"remaining_time":180.9452583},
{"learn":[180086.0757],"iteration":99,"passed_time":45.11508209,"remaining_time":180.4603284},
{"learn":[180027.9139],"iteration":100,"passed_time":45.57646341,"remaining_time":180.0495931},
{"learn":[179992.109],"iteration":101,"passed_time":46.72622788,"remaining_time":182.3239088},
{"learn":[179950.1469],"iteration":102,"passed_time":47.19687031,"remaining_time":181.9141506},
{"learn":[179934.8296],"iteration":103,"passed_time":47.52046741,"remaining_time":180.9433182},
{"learn":[179889.0332],"iteration":104,"passed_time":48.1238894,"remaining_time":181.0374887},
{"learn":[179874.7421],"iteration":105,"passed_time":48.90478448,"remaining_time":181.7781612},
{"learn":[179848.7338],"iteration":106,"passed_time":49.31972387,"remaining_time":181.1462755},
{"learn":[179845.0067],"iteration":107,"passed_time":49.83100566,"remaining_time":180.8680946},
{"learn":[179841.4492],"iteration":108,"passed_time":50.21369943,"remaining_time":180.1243714},
{"learn":[179822.3329],"iteration":109,"passed_time":50.84828447,"remaining_time":180.2802813},
{"learn":[179819.1158],"iteration":110,"passed_time":51.23404898,"remaining_time":179.5499554},
{"learn":[179812.2285],"iteration":111,"passed_time":51.65434576,"remaining_time":178.9454121},
{"learn":[179809.1755],"iteration":112,"passed_time":51.94054068,"remaining_time":177.8848606},
{"learn":[179780.4564],"iteration":113,"passed_time":52.97975177,"remaining_time":179.3875805},
{"learn":[179737.0032],"iteration":114,"passed_time":53.49978303,"remaining_time":179.1079693},
{"learn":[179732.1932],"iteration":115,"passed_time":53.92250312,"remaining_time":178.5020793},
{"learn":[179721.9166],"iteration":116,"passed_time":54.58295724,"remaining_time":178.6775438},
{"learn":[179719.5352],"iteration":117,"passed_time":55.02967256,"remaining_time":178.1469061},
{"learn":[179705.4119],"iteration":118,"passed_time":55.49587492,"remaining_time":177.6800701},
{"learn":[179663.471],"iteration":119,"passed_time":55.854749,"remaining_time":176.8733718},
{"learn":[179661.1497],"iteration":120,"passed_time":56.11491364,"remaining_time":175.7648948},
{"learn":[179620.3794],"iteration":121,"passed_time":56.48215213,"remaining_time":175.0020779},
{"learn":[179559.9187],"iteration":122,"passed_time":57.00123212,"remaining_time":174.7110936},
{"learn":[179519.045],"iteration":123,"passed_time":57.67934569,"remaining_time":174.8986611},
{"learn":[179499.1237],"iteration":124,"passed_time":58.15150944,"remaining_time":174.4545283},
{"learn":[179418.281],"iteration":125,"passed_time":58.74885646,"remaining_time":174.3815263},
{"learn":[179355.0271],"iteration":126,"passed_time":59.3640277,"remaining_time":174.3526168},
{"learn":[179336.3783],"iteration":127,"passed_time":59.74964597,"remaining_time":173.6474086},
{"learn":[179327.2455],"iteration":128,"passed_time":60.15014939,"remaining_time":172.9899645},
{"learn":[179295.6169],"iteration":129,"passed_time":60.7259197,"remaining_time":172.8353099},
{"learn":[179257.9495],"iteration":130,"passed_time":61.43806639,"remaining_time":173.0583702},
{"learn":[179215.9293],"iteration":131,"passed_time":62.34475136,"remaining_time":173.8096099},
{"learn":[179214.0529],"iteration":132,"passed_time":62.68411356,"remaining_time":172.9704487},
{"learn":[179184.137],"iteration":133,"passed_time":63.1001433,"remaining_time":172.3481526},
{"learn":[179179.6553],"iteration":134,"passed_time":63.56442978,"remaining_time":171.8593842},
{"learn":[179169.3158],"iteration":135,"passed_time":64.08876037,"remaining_time":171.5316822},
{"learn":[179139.8087],"iteration":136,"passed_time":64.40042777,"remaining_time":170.6376298},
{"learn":[179138.0409],"iteration":137,"passed_time":64.88067137,"remaining_time":170.1942249},
{"learn":[179129.7702],"iteration":138,"passed_time":65.44140554,"remaining_time":169.9593338},
{"learn":[179128.1297],"iteration":139,"passed_time":65.92582969,"remaining_time":169.5235621},
{"learn":[179126.573],"iteration":140,"passed_time":66.56479793,"remaining_time":169.4805848},
{"learn":[179126.4736],"iteration":141,"passed_time":66.92599136,"remaining_time":168.7289078},
{"learn":[179074.9511],"iteration":142,"passed_time":67.66162494,"remaining_time":168.9174832},
{"learn":[179068.1377],"iteration":143,"passed_time":68.0669479,"remaining_time":168.2766212},
{"learn":[179066.6763],"iteration":144,"passed_time":68.69619626,"remaining_time":168.1872391},
{"learn":[179026.7788],"iteration":145,"passed_time":69.02467436,"remaining_time":167.3611967},
{"learn":[178989.8057],"iteration":146,"passed_time":69.4732797,"remaining_time":166.8303927},
{"learn":[178983.6376],"iteration":147,"passed_time":70.50227848,"remaining_time":167.6810948},
{"learn":[178982.0367],"iteration":148,"passed_time":70.99187106,"remaining_time":167.2358842},
{"learn":[178975.5635],"iteration":149,"passed_time":71.64491229,"remaining_time":167.171462},
{"learn":[178941.9641],"iteration":150,"passed_time":72.21381947,"remaining_time":166.904788},
{"learn":[178933.2514],"iteration":151,"passed_time":72.67245616,"remaining_time":166.3816759},
{"learn":[178901.3365],"iteration":152,"passed_time":73.16328742,"remaining_time":165.9324231},
{"learn":[178874.4988],"iteration":153,"passed_time":73.46998862,"remaining_time":165.0689355},
{"learn":[178865.7252],"iteration":154,"passed_time":74.02533965,"remaining_time":164.7660786},
{"learn":[178860.8887],"iteration":155,"passed_time":74.77658213,"remaining_time":164.8919503},
{"learn":[178820.8277],"iteration":156,"passed_time":75.24309135,"remaining_time":164.3845881},
{"learn":[178803.9253],"iteration":157,"passed_time":75.82826434,"remaining_time":164.1345975},
{"learn":[178799.6175],"iteration":158,"passed_time":76.39836928,"remaining_time":163.848075},
{"learn":[178795.4294],"iteration":159,"passed_time":76.72662902,"remaining_time":163.0440867},
{"learn":[178778.8333],"iteration":160,"passed_time":77.30688706,"remaining_time":162.7766131},
{"learn":[178760.7248],"iteration":161,"passed_time":77.71212432,"remaining_time":162.1401112},
{"learn":[178745.5125],"iteration":162,"passed_time":78.15138709,"remaining_time":161.5767942},
{"learn":[178723.3304],"iteration":163,"passed_time":78.79470135,"remaining_time":161.4330467},
{"learn":[178710.347],"iteration":164,"passed_time":79.41740719,"remaining_time":161.2414025},
{"learn":[178707.4268],"iteration":165,"passed_time":79.86687339,"remaining_time":160.6959983},
{"learn":[178689.1695],"iteration":166,"passed_time":80.52235655,"remaining_time":160.5625433},
{"learn":[178681.4445],"iteration":167,"passed_time":81.05817175,"remaining_time":160.186387},
{"learn":[178660.546],"iteration":168,"passed_time":81.54980417,"remaining_time":159.7218058},
{"learn":[178642.351],"iteration":169,"passed_time":82.04931534,"remaining_time":159.2722004},
{"learn":[178621.671],"iteration":170,"passed_time":82.69285126,"remaining_time":159.0991115},
{"learn":[178571.2088],"iteration":171,"passed_time":83.17860324,"remaining_time":158.619662},
{"learn":[178546.0262],"iteration":172,"passed_time":83.79461923,"remaining_time":158.3863612},
{"learn":[178541.6601],"iteration":173,"passed_time":84.18202651,"remaining_time":157.7203485},
{"learn":[178540.7538],"iteration":174,"passed_time":84.62732792,"remaining_time":157.1650376},
{"learn":[178534.6955],"iteration":175,"passed_time":85.82846598,"remaining_time":158.0024033},
{"learn":[178493.1346],"iteration":176,"passed_time":86.8007252,"remaining_time":158.3990635},
{"learn":[178484.9267],"iteration":177,"passed_time":87.42605542,"remaining_time":158.1527519},
{"learn":[178481.0818],"iteration":178,"passed_time":88.5882064,"remaining_time":158.8648841},
{"learn":[178467.5457],"iteration":179,"passed_time":90.01071839,"remaining_time":160.0190549},
{"learn":[178457.3645],"iteration":180,"passed_time":91.34915258,"remaining_time":160.9965728},
{"learn":[178453.7211],"iteration":181,"passed_time":91.8706378,"remaining_time":160.5212243},
{"learn":[178404.4701],"iteration":182,"passed_time":92.30892575,"remaining_time":159.9012539},
{"learn":[178374.636],"iteration":183,"passed_time":92.61721402,"remaining_time":159.059998},
{"learn":[178359.416],"iteration":184,"passed_time":93.0503929,"remaining_time":158.4371555},
{"learn":[178358.7295],"iteration":185,"passed_time":93.5692364,"remaining_time":157.960969},
{"learn":[178358.0787],"iteration":186,"passed_time":94.03279538,"remaining_time":157.3917912},
{"learn":[178343.8522],"iteration":187,"passed_time":94.96610614,"remaining_time":157.6033251},
{"learn":[178300.5417],"iteration":188,"passed_time":95.39951659,"remaining_time":156.9801569},
{"learn":[178279.1377],"iteration":189,"passed_time":95.94744873,"remaining_time":156.5458374},
{"learn":[178252.7479],"iteration":190,"passed_time":96.75248365,"remaining_time":156.5262694},
{"learn":[178246.1272],"iteration":191,"passed_time":97.36884974,"remaining_time":156.1958631},
{"learn":[178243.2588],"iteration":192,"passed_time":97.73639876,"remaining_time":155.4667068},
{"learn":[178242.73],"iteration":193,"passed_time":98.37097992,"remaining_time":155.1624735},
{"learn":[178220.3594],"iteration":194,"passed_time":98.78478034,"remaining_time":154.5095282},
{"learn":[178201.1195],"iteration":195,"passed_time":99.15552628,"remaining_time":153.7922448},
{"learn":[178198.3951],"iteration":196,"passed_time":99.80711526,"remaining_time":153.5104362},
{"learn":[178196.077],"iteration":197,"passed_time":100.3656386,"remaining_time":153.0829437},
{"learn":[178190.6196],"iteration":198,"passed_time":101.2986754,"remaining_time":153.2206095},
{"learn":[178181.5778],"iteration":199,"passed_time":102.4001146,"remaining_time":153.6001719},
{"learn":[178173.8778],"iteration":200,"passed_time":102.7875577,"remaining_time":152.9028844},
{"learn":[178145.3751],"iteration":201,"passed_time":103.7204955,"remaining_time":153.0134042},
{"learn":[178139.2641],"iteration":202,"passed_time":104.5920484,"remaining_time":153.0238343},
{"learn":[178105.6089],"iteration":203,"passed_time":105.0222145,"remaining_time":152.385174},
{"learn":[178075.7222],"iteration":204,"passed_time":105.5733222,"remaining_time":151.9225856},
{"learn":[178042.9652],"iteration":205,"passed_time":105.9790618,"remaining_time":151.2516708},
{"learn":[178022.1844],"iteration":206,"passed_time":106.5740818,"remaining_time":150.8512365},
{"learn":[178016.6544],"iteration":207,"passed_time":106.9017645,"remaining_time":150.073631},
{"learn":[178014.6344],"iteration":208,"passed_time":107.5360343,"remaining_time":149.7272056},
{"learn":[178011.4081],"iteration":209,"passed_time":107.996055,"remaining_time":149.1374093},
{"learn":[178002.2321],"iteration":210,"passed_time":108.2859039,"remaining_time":148.3157641},
{"learn":[177989.1245],"iteration":211,"passed_time":108.8623563,"remaining_time":147.888484},
{"learn":[177959.5672],"iteration":212,"passed_time":109.3256727,"remaining_time":147.3073618},
{"learn":[177948.955],"iteration":213,"passed_time":110.485777,"remaining_time":147.6585618},
{"learn":[177873.0239],"iteration":214,"passed_time":111.5286446,"remaining_time":147.8402963},
{"learn":[177839.6715],"iteration":215,"passed_time":112.1376683,"remaining_time":147.4402676},
{"learn":[177810.7183],"iteration":216,"passed_time":112.5798448,"remaining_time":146.8207193},
{"learn":[177801.5906],"iteration":217,"passed_time":113.1176652,"remaining_time":146.326521},
{"learn":[177791.7743],"iteration":218,"passed_time":113.4920035,"remaining_time":145.6221598},
{"learn":[177782.7895],"iteration":219,"passed_time":114.5307519,"remaining_time":145.7664115},
{"learn":[177766.6155],"iteration":220,"passed_time":115.1934771,"remaining_time":145.4252494},
{"learn":[177766.2862],"iteration":221,"passed_time":115.9324884,"remaining_time":145.1767197},
{"learn":[177763.4288],"iteration":222,"passed_time":116.5121591,"remaining_time":144.7258658},
{"learn":[177758.2738],"iteration":223,"passed_time":116.8900014,"remaining_time":144.0251802},
{"learn":[177750.3292],"iteration":224,"passed_time":117.5642212,"remaining_time":143.6896037},
{"learn":[177695.7561],"iteration":225,"passed_time":118.6089701,"remaining_time":143.8002558},
{"learn":[177682.7642],"iteration":226,"passed_time":119.9090471,"remaining_time":144.2077968},
{"learn":[177676.2589],"iteration":227,"passed_time":120.6490232,"remaining_time":143.932168},
{"learn":[177670.965],"iteration":228,"passed_time":121.5034734,"remaining_time":143.7879532},
{"learn":[177664.6808],"iteration":229,"passed_time":122.4775149,"remaining_time":143.7779522},
{"learn":[177654.5844],"iteration":230,"passed_time":123.3318272,"remaining_time":143.6201798},
{"learn":[177643.0858],"iteration":231,"passed_time":123.8337414,"remaining_time":143.0493219},
{"learn":[177623.3268],"iteration":232,"passed_time":124.5717726,"remaining_time":142.7496278},
{"learn":[177612.9729],"iteration":233,"passed_time":125.417962,"remaining_time":142.5691363},
{"learn":[177596.2425],"iteration":234,"passed_time":126.5148781,"remaining_time":142.6657136},
{"learn":[177590.9679],"iteration":235,"passed_time":127.1015696,"remaining_time":142.1814169},
{"learn":[177576.4037],"iteration":236,"passed_time":127.4804459,"remaining_time":141.4656425},
{"learn":[177574.2618],"iteration":237,"passed_time":128.0013184,"remaining_time":140.9090144},
{"learn":[177551.2116],"iteration":238,"passed_time":129.2245482,"remaining_time":141.1196948},
{"learn":[177539.037],"iteration":239,"passed_time":129.7498899,"remaining_time":140.5623808},
{"learn":[177477.7795],"iteration":240,"passed_time":130.2860834,"remaining_time":140.0169942},
{"learn":[177464.6056],"iteration":241,"passed_time":131.308116,"remaining_time":139.9896443},
{"learn":[177445.4749],"iteration":242,"passed_time":132.0047575,"remaining_time":139.6099698},
{"learn":[177435.6056],"iteration":243,"passed_time":132.7928894,"remaining_time":139.3236872},
{"learn":[177391.4911],"iteration":244,"passed_time":133.2141843,"remaining_time":138.651498},
{"learn":[177375.4165],"iteration":245,"passed_time":133.7620499,"remaining_time":138.1120353},
{"learn":[177370.3303],"iteration":246,"passed_time":134.3876814,"remaining_time":137.6521595},
{"learn":[177320.2184],"iteration":247,"passed_time":134.8091762,"remaining_time":136.9835178},
{"learn":[177315.933],"iteration":248,"passed_time":135.3612891,"remaining_time":136.4485283},
{"learn":[177304.6018],"iteration":249,"passed_time":136.6732318,"remaining_time":136.6732318},
{"learn":[177299.8618],"iteration":250,"passed_time":137.1807486,"remaining_time":136.0876749},
{"learn":[177291.5879],"iteration":251,"passed_time":138.268051,"remaining_time":136.07332},
{"learn":[177290.5328],"iteration":252,"passed_time":138.969728,"remaining_time":135.6740033},
{"learn":[177282.8686],"iteration":253,"passed_time":139.4637352,"remaining_time":135.0711766},
{"learn":[177273.6016],"iteration":254,"passed_time":139.8669219,"remaining_time":134.3819445},
{"learn":[177270.8031],"iteration":255,"passed_time":140.7987717,"remaining_time":134.1988293},
{"learn":[177259.2928],"iteration":256,"passed_time":142.1474831,"remaining_time":134.4040404},
{"learn":[177237.5003],"iteration":257,"passed_time":143.06194,"remaining_time":134.1898817},
{"learn":[177233.9086],"iteration":258,"passed_time":143.9314622,"remaining_time":133.9285035},
{"learn":[177208.7845],"iteration":259,"passed_time":144.7741616,"remaining_time":133.6376876},
{"learn":[177206.8921],"iteration":260,"passed_time":145.6108225,"remaining_time":133.3371134},
{"learn":[177205.116],"iteration":261,"passed_time":146.4279574,"remaining_time":133.0147094},
{"learn":[177164.2841],"iteration":262,"passed_time":147.2950945,"remaining_time":132.7336023},
{"learn":[177160.4084],"iteration":263,"passed_time":147.9340885,"remaining_time":132.2441094},
{"learn":[177147.728],"iteration":264,"passed_time":148.4729628,"remaining_time":131.6647029},
{"learn":[177138.2128],"iteration":265,"passed_time":149.3508334,"remaining_time":131.3838158},
{"learn":[177132.5414],"iteration":266,"passed_time":149.9064177,"remaining_time":130.817211},
{"learn":[177125.794],"iteration":267,"passed_time":150.3503989,"remaining_time":130.1540767},
{"learn":[177116.4444],"iteration":268,"passed_time":150.8921947,"remaining_time":129.5765687},
{"learn":[177114.3925],"iteration":269,"passed_time":151.5171977,"remaining_time":129.0702054},
{"learn":[177103.094],"iteration":270,"passed_time":152.2681283,"remaining_time":128.6693778},
{"learn":[177099.9461],"iteration":271,"passed_time":153.1568936,"remaining_time":128.3815138},
{"learn":[177097.9313],"iteration":272,"passed_time":154.3345067,"remaining_time":128.329425},
{"learn":[177096.2837],"iteration":273,"passed_time":154.8816977,"remaining_time":127.7491375},
{"learn":[177088.5402],"iteration":274,"passed_time":155.6634416,"remaining_time":127.3609977},
{"learn":[177081.5291],"iteration":275,"passed_time":156.5559125,"remaining_time":127.059871},
{"learn":[177069.474],"iteration":276,"passed_time":157.5335168,"remaining_time":126.8230117},
{"learn":[177066.9193],"iteration":277,"passed_time":158.0574321,"remaining_time":126.2185249},
{"learn":[177042.515],"iteration":278,"passed_time":158.7510672,"remaining_time":125.7490532},
{"learn":[177034.2465],"iteration":279,"passed_time":159.406839,"remaining_time":125.2482306},
{"learn":[177031.898],"iteration":280,"passed_time":160.1771841,"remaining_time":124.835599},
{"learn":[177028.3918],"iteration":281,"passed_time":160.9587088,"remaining_time":124.4290728},
{"learn":[177015.3107],"iteration":282,"passed_time":161.6495648,"remaining_time":123.950373},
{"learn":[177012.0609],"iteration":283,"passed_time":162.3424951,"remaining_time":123.4717569},
{"learn":[177000.0017],"iteration":284,"passed_time":163.0442274,"remaining_time":122.9982768},
{"learn":[176998.3899],"iteration":285,"passed_time":163.8467747,"remaining_time":122.5986356},
{"learn":[176993.6431],"iteration":286,"passed_time":164.3263116,"remaining_time":121.9564612},
{"learn":[176960.5654],"iteration":287,"passed_time":165.5284305,"remaining_time":121.8473169},
{"learn":[176949.5627],"iteration":288,"passed_time":166.2341434,"remaining_time":121.3681808},
{"learn":[176948.4198],"iteration":289,"passed_time":166.8764023,"remaining_time":120.8415327},
{"learn":[176945.9505],"iteration":290,"passed_time":167.5010294,"remaining_time":120.3014266},
{"learn":[176944.3549],"iteration":291,"passed_time":168.2030773,"remaining_time":119.8158907},
{"learn":[176939.7069],"iteration":292,"passed_time":168.6278173,"remaining_time":119.1329631},
{"learn":[176929.5472],"iteration":293,"passed_time":169.0563178,"remaining_time":118.4544268},
{"learn":[176927.1583],"iteration":294,"passed_time":169.5410892,"remaining_time":117.8166891},
{"learn":[176900.0092],"iteration":295,"passed_time":170.2553524,"remaining_time":117.3381483},
{"learn":[176865.1317],"iteration":296,"passed_time":170.9638888,"remaining_time":116.8541058},
{"learn":[176855.8014],"iteration":297,"passed_time":171.5521488,"remaining_time":116.2870271},
{"learn":[176854.8249],"iteration":298,"passed_time":171.9897082,"remaining_time":115.6184995},
{"learn":[176851.5821],"iteration":299,"passed_time":172.6801672,"remaining_time":115.1201115},
{"learn":[176838.0776],"iteration":300,"passed_time":173.305822,"remaining_time":114.5776033},
{"learn":[176836.6804],"iteration":301,"passed_time":174.125374,"remaining_time":114.1616691},
{"learn":[176832.0631],"iteration":302,"passed_time":175.010696,"remaining_time":113.785832},
{"learn":[176827.9246],"iteration":303,"passed_time":175.5839934,"remaining_time":113.2054694},
{"learn":[176826.4175],"iteration":304,"passed_time":175.9961073,"remaining_time":112.5221014},
{"learn":[176815.4931],"iteration":305,"passed_time":176.5170123,"remaining_time":111.9094784},
{"learn":[176806.5799],"iteration":306,"passed_time":176.9318407,"remaining_time":111.2307663},
{"learn":[176805.9958],"iteration":307,"passed_time":177.3944908,"remaining_time":110.5835787},
{"learn":[176801.2371],"iteration":308,"passed_time":177.767324,"remaining_time":109.8820676},
{"learn":[176786.2319],"iteration":309,"passed_time":178.3486196,"remaining_time":109.3104443},
{"learn":[176776.9766],"iteration":310,"passed_time":179.2730804,"remaining_time":108.9473061},
{"learn":[176774.6109],"iteration":311,"passed_time":179.9931351,"remaining_time":108.4574019},
{"learn":[176766.9725],"iteration":312,"passed_time":180.4619635,"remaining_time":107.8159334},
{"learn":[176765.6218],"iteration":313,"passed_time":180.8300542,"remaining_time":107.115892},
{"learn":[176763.5773],"iteration":314,"passed_time":181.3514698,"remaining_time":106.5080061},
{"learn":[176761.616],"iteration":315,"passed_time":182.0833602,"remaining_time":106.0232224},
{"learn":[176750.2845],"iteration":316,"passed_time":182.8384606,"remaining_time":105.5502785},
{"learn":[176745.4393],"iteration":317,"passed_time":183.27415,"remaining_time":104.8927525},
{"learn":[176743.9982],"iteration":318,"passed_time":184.2914779,"remaining_time":104.5666379},
{"learn":[176734.9566],"iteration":319,"passed_time":185.1776121,"remaining_time":104.1624068},
{"learn":[176723.565],"iteration":320,"passed_time":185.87647,"remaining_time":103.6507419},
{"learn":[176719.1435],"iteration":321,"passed_time":186.9449582,"remaining_time":103.342244},
{"learn":[176681.6619],"iteration":322,"passed_time":187.4571455,"remaining_time":102.7241943},
{"learn":[176679.1193],"iteration":323,"passed_time":188.4074141,"remaining_time":102.3447681},
{"learn":[176672.9393],"iteration":324,"passed_time":189.1003048,"remaining_time":101.8232411},
{"learn":[176639.4986],"iteration":325,"passed_time":189.6558099,"remaining_time":101.2273341},
{"learn":[176629.9694],"iteration":326,"passed_time":190.6052828,"remaining_time":100.8401037},
{"learn":[176626.3326],"iteration":327,"passed_time":191.2170662,"remaining_time":100.272364},
{"learn":[176571.6286],"iteration":328,"passed_time":192.0890422,"remaining_time":99.83959335},
{"learn":[176563.2379],"iteration":329,"passed_time":192.984299,"remaining_time":99.41615405},
{"learn":[176561.064],"iteration":330,"passed_time":194.2494564,"remaining_time":99.17872547},
{"learn":[176559.926],"iteration":331,"passed_time":195.1820182,"remaining_time":98.76680437},
{"learn":[176524.5914],"iteration":332,"passed_time":196.1684064,"remaining_time":98.37875034},
{"learn":[176511.0097],"iteration":333,"passed_time":197.0432114,"remaining_time":97.93165595},
{"learn":[176501.7368],"iteration":334,"passed_time":198.3378606,"remaining_time":97.68879703},
{"learn":[176493.1135],"iteration":335,"passed_time":198.9460984,"remaining_time":97.10464325},
{"learn":[176479.1317],"iteration":336,"passed_time":200.138565,"remaining_time":96.80292612},
{"learn":[176474.6015],"iteration":337,"passed_time":200.8023195,"remaining_time":96.24253183},
{"learn":[176473.8123],"iteration":338,"passed_time":201.6576642,"remaining_time":95.77251899},
{"learn":[176469.5952],"iteration":339,"passed_time":202.4175757,"remaining_time":95.25532973},
{"learn":[176467.8561],"iteration":340,"passed_time":203.5861135,"remaining_time":94.92724941},
{"learn":[176458.5704],"iteration":341,"passed_time":204.025922,"remaining_time":94.25758968},
{"learn":[176456.8761],"iteration":342,"passed_time":204.5724411,"remaining_time":93.63811444},
{"learn":[176455.4488],"iteration":343,"passed_time":205.1543828,"remaining_time":93.03512706},
{"learn":[176451.571],"iteration":344,"passed_time":205.6886233,"remaining_time":92.41083076},
{"learn":[176425.1534],"iteration":345,"passed_time":206.8378239,"remaining_time":92.06076556},
{"learn":[176419.2785],"iteration":346,"passed_time":207.8730444,"remaining_time":91.65583803},
{"learn":[176419.2275],"iteration":347,"passed_time":208.9885243,"remaining_time":91.28234395},
{"learn":[176418.2218],"iteration":348,"passed_time":209.8647651,"remaining_time":90.80108748},
{"learn":[176416.5339],"iteration":349,"passed_time":210.6632149,"remaining_time":90.28423495},
{"learn":[176415.0779],"iteration":350,"passed_time":211.7710118,"remaining_time":89.89709617},
{"learn":[176398.4651],"iteration":351,"passed_time":213.2941181,"remaining_time":89.68048146},
{"learn":[176393.5288],"iteration":352,"passed_time":214.2021025,"remaining_time":89.20030895},
{"learn":[176392.1914],"iteration":353,"passed_time":214.8814084,"remaining_time":88.62340572},
{"learn":[176391.9385],"iteration":354,"passed_time":215.7339911,"remaining_time":88.11670059},
{"learn":[176386.7966],"iteration":355,"passed_time":216.6626394,"remaining_time":87.63882044},
{"learn":[176385.3484],"iteration":356,"passed_time":217.8682418,"remaining_time":87.26935175},
{"learn":[176382.4606],"iteration":357,"passed_time":218.4516782,"remaining_time":86.64843104},
{"learn":[176380.5094],"iteration":358,"passed_time":219.0884737,"remaining_time":86.04867632},
{"learn":[176378.8811],"iteration":359,"passed_time":220.4782847,"remaining_time":85.74155516},
{"learn":[176375.6582],"iteration":360,"passed_time":221.197418,"remaining_time":85.17019696},
{"learn":[176354.1499],"iteration":361,"passed_time":222.2187451,"remaining_time":84.71322326},
{"learn":[176329.5772],"iteration":362,"passed_time":223.4395098,"remaining_time":84.32841002},
{"learn":[176324.5662],"iteration":363,"passed_time":224.6593697,"remaining_time":83.93866562},
{"learn":[176323.5804],"iteration":364,"passed_time":226.02774,"remaining_time":83.5993011},
{"learn":[176321.2239],"iteration":365,"passed_time":226.6515475,"remaining_time":82.9817141},
{"learn":[176318.2712],"iteration":366,"passed_time":227.4622015,"remaining_time":82.431806},
{"learn":[176303.0368],"iteration":367,"passed_time":228.6233958,"remaining_time":82.00621807},
{"learn":[176302.0342],"iteration":368,"passed_time":229.6894096,"remaining_time":81.54285273},
{"learn":[176297.1951],"iteration":369,"passed_time":231.120813,"remaining_time":81.20460998},
{"learn":[176293.3394],"iteration":370,"passed_time":231.8141245,"remaining_time":80.60383304},
{"learn":[176289.9592],"iteration":371,"passed_time":232.3947441,"remaining_time":79.96378292},
{"learn":[176286.9943],"iteration":372,"passed_time":232.7965177,"remaining_time":79.26315749},
{"learn":[176282.8236],"iteration":373,"passed_time":233.5361633,"remaining_time":78.67795874},
{"learn":[176277.2676],"iteration":374,"passed_time":234.5742029,"remaining_time":78.19140096},
{"learn":[176275.7267],"iteration":375,"passed_time":235.0604393,"remaining_time":77.51993212},
{"learn":[176274.3926],"iteration":376,"passed_time":235.4937079,"remaining_time":76.83216464},
{"learn":[176261.3766],"iteration":377,"passed_time":236.0309049,"remaining_time":76.17928678},
{"learn":[176246.7005],"iteration":378,"passed_time":236.9936723,"remaining_time":75.66288747},
{"learn":[176242.6539],"iteration":379,"passed_time":237.9180828,"remaining_time":75.13202616},
{"learn":[176241.5295],"iteration":380,"passed_time":238.6151385,"remaining_time":74.52808787},
{"learn":[176236.3999],"iteration":381,"passed_time":239.4028799,"remaining_time":73.95167494},
{"learn":[176236.3532],"iteration":382,"passed_time":240.4256704,"remaining_time":73.44596197},
{"learn":[176235.3162],"iteration":383,"passed_time":241.2387475,"remaining_time":72.87420499},
{"learn":[176222.7307],"iteration":384,"passed_time":242.0198503,"remaining_time":72.29164359},
{"learn":[176219.3796],"iteration":385,"passed_time":243.4519587,"remaining_time":71.9003194},
{"learn":[176218.6432],"iteration":386,"passed_time":245.0413513,"remaining_time":71.54954186},
{"learn":[176218.5987],"iteration":387,"passed_time":246.1203542,"remaining_time":71.0450507},
{"learn":[176216.0923],"iteration":388,"passed_time":247.0581926,"remaining_time":70.49732489},
{"learn":[176216.052],"iteration":389,"passed_time":247.5590681,"remaining_time":69.82435254},
{"learn":[176213.9205],"iteration":390,"passed_time":247.9376092,"remaining_time":69.11815705},
{"learn":[176212.9287],"iteration":391,"passed_time":248.6806709,"remaining_time":68.51406239},
{"learn":[176212.6724],"iteration":392,"passed_time":249.7196225,"remaining_time":67.98982089},
{"learn":[176211.3965],"iteration":393,"passed_time":250.670451,"remaining_time":67.4392584},
{"learn":[176208.6214],"iteration":394,"passed_time":251.1740557,"remaining_time":66.76778697},
{"learn":[176204.4022],"iteration":395,"passed_time":252.2425104,"remaining_time":66.24550777},
{"learn":[176203.0882],"iteration":396,"passed_time":254.344211,"remaining_time":65.98854845},
{"learn":[176201.0529],"iteration":397,"passed_time":256.094244,"remaining_time":65.6321932},
{"learn":[176188.0223],"iteration":398,"passed_time":257.2697738,"remaining_time":65.12342646},
{"learn":[176186.3157],"iteration":399,"passed_time":258.3888928,"remaining_time":64.59722319},
{"learn":[176176.8456],"iteration":400,"passed_time":259.0527394,"remaining_time":63.95566383},
{"learn":[176173.0357],"iteration":401,"passed_time":260.3588871,"remaining_time":63.47057448},
{"learn":[176172.4087],"iteration":402,"passed_time":261.2061335,"remaining_time":62.87095522},
{"learn":[176170.8537],"iteration":403,"passed_time":262.2888626,"remaining_time":62.32606636},
{"learn":[176169.5092],"iteration":404,"passed_time":263.1913151,"remaining_time":61.73623441},
{"learn":[176166.2326],"iteration":405,"passed_time":264.1742426,"remaining_time":61.1634946},
{"learn":[176165.6413],"iteration":406,"passed_time":265.5502465,"remaining_time":60.67855756},
{"learn":[176163.945],"iteration":407,"passed_time":266.3504549,"remaining_time":60.05941629},
{"learn":[176163.3984],"iteration":408,"passed_time":267.1608721,"remaining_time":59.44166102},
{"learn":[176152.4259],"iteration":409,"passed_time":268.3156289,"remaining_time":58.89855268},
{"learn":[176151.014],"iteration":410,"passed_time":269.2721218,"remaining_time":58.3095349},
{"learn":[176149.7616],"iteration":411,"passed_time":269.8515328,"remaining_time":57.63819147},
{"learn":[176145.3921],"iteration":412,"passed_time":270.9249424,"remaining_time":57.07135591},
{"learn":[176142.3029],"iteration":413,"passed_time":272.2070566,"remaining_time":56.54542722},
{"learn":[176116.896],"iteration":414,"passed_time":273.4904959,"remaining_time":56.01612566},
{"learn":[176115.4042],"iteration":415,"passed_time":274.2334614,"remaining_time":55.37406431},
{"learn":[176110.5159],"iteration":416,"passed_time":275.4555687,"remaining_time":54.82688778},
{"learn":[176100.9725],"iteration":417,"passed_time":277.3651167,"remaining_time":54.41133869},
{"learn":[176099.2111],"iteration":418,"passed_time":278.3027772,"remaining_time":53.80077554},
{"learn":[176097.4119],"iteration":419,"passed_time":279.1336527,"remaining_time":53.16831481},
{"learn":[176096.5453],"iteration":420,"passed_time":280.3368269,"remaining_time":52.60477275},
{"learn":[176093.744],"iteration":421,"passed_time":281.4918564,"remaining_time":52.02930047},
{"learn":[176091.7102],"iteration":422,"passed_time":282.1657412,"remaining_time":51.36350371},
{"learn":[176090.8016],"iteration":423,"passed_time":283.6661685,"remaining_time":50.84582266},
{"learn":[176086.6077],"iteration":424,"passed_time":284.1179929,"remaining_time":50.13846933},
{"learn":[176085.4615],"iteration":425,"passed_time":284.6543894,"remaining_time":49.44700661},
{"learn":[176084.8551],"iteration":426,"passed_time":285.4844336,"remaining_time":48.80647225},
{"learn":[176079.7881],"iteration":427,"passed_time":286.0468228,"remaining_time":48.12002627},
{"learn":[176075.7756],"iteration":428,"passed_time":287.0488551,"remaining_time":47.50692007},
{"learn":[176075.329],"iteration":429,"passed_time":287.6804699,"remaining_time":46.8317044},
{"learn":[176063.607],"iteration":430,"passed_time":289.291386,"remaining_time":46.31347014},
{"learn":[176059.0429],"iteration":431,"passed_time":289.9112967,"remaining_time":45.63418559},
{"learn":[176055.7172],"iteration":432,"passed_time":290.716417,"remaining_time":44.98383358},
{"learn":[176051.6233],"iteration":433,"passed_time":291.5445186,"remaining_time":44.33626319},
{"learn":[176051.0841],"iteration":434,"passed_time":292.2985347,"remaining_time":43.67679254},
{"learn":[176051.0363],"iteration":435,"passed_time":293.7305827,"remaining_time":43.11641582},
{"learn":[176050.9909],"iteration":436,"passed_time":294.1832905,"remaining_time":42.4108634},
{"learn":[176047.2887],"iteration":437,"passed_time":294.8693132,"remaining_time":41.73949182},
{"learn":[176045.8626],"iteration":438,"passed_time":295.5583429,"remaining_time":41.06847133},
{"learn":[176032.3345],"iteration":439,"passed_time":295.9875609,"remaining_time":40.36194012},
{"learn":[176028.4607],"iteration":440,"passed_time":296.6975904,"remaining_time":39.69423545},
{"learn":[176027.2109],"iteration":441,"passed_time":297.1517888,"remaining_time":38.99276866},
{"learn":[176023.9889],"iteration":442,"passed_time":297.9489621,"remaining_time":38.33654817},
{"learn":[176021.0645],"iteration":443,"passed_time":298.5975767,"remaining_time":37.66095561},
{"learn":[176019.9657],"iteration":444,"passed_time":299.5079352,"remaining_time":37.01783469},
{"learn":[176017.2789],"iteration":445,"passed_time":300.2494165,"remaining_time":36.35306836},
{"learn":[176015.953],"iteration":446,"passed_time":301.0124978,"remaining_time":35.69051987},
{"learn":[176015.2422],"iteration":447,"passed_time":301.6763752,"remaining_time":35.01600784},
{"learn":[176015.2001],"iteration":448,"passed_time":302.337276,"remaining_time":34.34120506},
{"learn":[176014.0474],"iteration":449,"passed_time":302.8782622,"remaining_time":33.65314025},
{"learn":[176013.4492],"iteration":450,"passed_time":303.4895649,"remaining_time":32.97336736},
{"learn":[176012.9396],"iteration":451,"passed_time":304.0695199,"remaining_time":32.29056848},
{"learn":[176012.3512],"iteration":452,"passed_time":305.1785645,"remaining_time":31.66311817},
{"learn":[176002.104],"iteration":453,"passed_time":305.6299833,"remaining_time":30.96691461},
{"learn":[176001.1492],"iteration":454,"passed_time":306.5636961,"remaining_time":30.31948643},
{"learn":[175999.9431],"iteration":455,"passed_time":307.9701275,"remaining_time":29.71641582},
{"learn":[175985.2278],"iteration":456,"passed_time":309.5533932,"remaining_time":29.12646807},
{"learn":[175974.3602],"iteration":457,"passed_time":310.20654,"remaining_time":28.44688795},
{"learn":[175971.9435],"iteration":458,"passed_time":310.6519875,"remaining_time":27.74887034},
{"learn":[175969.2149],"iteration":459,"passed_time":311.2375523,"remaining_time":27.06413499},
{"learn":[175967.0029],"iteration":460,"passed_time":311.653529,"remaining_time":26.36548293},
{"learn":[175958.5986],"iteration":461,"passed_time":312.0952966,"remaining_time":25.67017591},
{"learn":[175958.0176],"iteration":462,"passed_time":312.5459736,"remaining_time":24.97667607},
{"learn":[175957.4898],"iteration":463,"passed_time":313.1520678,"remaining_time":24.29628112},
{"learn":[175955.953],"iteration":464,"passed_time":313.5687831,"remaining_time":23.60195141},
{"learn":[175955.9202],"iteration":465,"passed_time":314.1290339,"remaining_time":22.91928573},
{"learn":[175953.356],"iteration":466,"passed_time":315.0839772,"remaining_time":22.26503479},
{"learn":[175953.325],"iteration":467,"passed_time":315.5089214,"remaining_time":21.57325958},
{"learn":[175952.841],"iteration":468,"passed_time":315.8550211,"remaining_time":20.87741078},
{"learn":[175951.4448],"iteration":469,"passed_time":316.8348947,"remaining_time":20.22350392},
{"learn":[175950.4613],"iteration":470,"passed_time":317.2905237,"remaining_time":19.53593458},
{"learn":[175948.2325],"iteration":471,"passed_time":317.9189858,"remaining_time":18.85960085},
{"learn":[175946.8797],"iteration":472,"passed_time":318.6657273,"remaining_time":18.19022122},
{"learn":[175946.4519],"iteration":473,"passed_time":319.2377547,"remaining_time":17.51093169},
{"learn":[175942.6891],"iteration":474,"passed_time":320.1215665,"remaining_time":16.8485035},
{"learn":[175932.4952],"iteration":475,"passed_time":320.9707007,"remaining_time":16.18339667},
{"learn":[175931.9193],"iteration":476,"passed_time":321.5639733,"remaining_time":15.5051811},
{"learn":[175930.3381],"iteration":477,"passed_time":322.3362889,"remaining_time":14.83556141},
{"learn":[175928.4668],"iteration":478,"passed_time":323.0221728,"remaining_time":14.16172365},
{"learn":[175917.6672],"iteration":479,"passed_time":323.4499229,"remaining_time":13.47708012},
{"learn":[175915.2571],"iteration":480,"passed_time":323.9766465,"remaining_time":12.79741431},
{"learn":[175914.0862],"iteration":481,"passed_time":324.6196258,"remaining_time":12.12272461},
{"learn":[175914.0052],"iteration":482,"passed_time":325.2312348,"remaining_time":11.44706209},
{"learn":[175912.0484],"iteration":483,"passed_time":325.6744405,"remaining_time":10.76609721},
{"learn":[175908.9042],"iteration":484,"passed_time":326.4991057,"remaining_time":10.09791049},
{"learn":[175907.2356],"iteration":485,"passed_time":327.3614108,"remaining_time":9.430164096},
{"learn":[175903.9649],"iteration":486,"passed_time":327.8519987,"remaining_time":8.751696063},
{"learn":[175902.8309],"iteration":487,"passed_time":328.3833879,"remaining_time":8.075001341},
{"learn":[175901.9795],"iteration":488,"passed_time":328.7579619,"remaining_time":7.395373377},
{"learn":[175900.6224],"iteration":489,"passed_time":329.2875414,"remaining_time":6.720153907},
{"learn":[175898.2018],"iteration":490,"passed_time":329.7422477,"remaining_time":6.044155254},
{"learn":[175897.086],"iteration":491,"passed_time":330.717412,"remaining_time":5.377518894},
{"learn":[175889.2315],"iteration":492,"passed_time":331.0924566,"remaining_time":4.701109931},
{"learn":[175889.1706],"iteration":493,"passed_time":331.5839423,"remaining_time":4.027335332},
{"learn":[175886.4358],"iteration":494,"passed_time":332.853034,"remaining_time":3.362151859},
{"learn":[175885.8817],"iteration":495,"passed_time":333.2950813,"remaining_time":2.687863559},
{"learn":[175885.1216],"iteration":496,"passed_time":333.9286221,"remaining_time":2.015665727},
{"learn":[175885.0364],"iteration":497,"passed_time":334.4926326,"remaining_time":1.343343906},
{"learn":[175879.3312],"iteration":498,"passed_time":334.917439,"remaining_time":0.6711772324},
{"learn":[175878.4342],"iteration":499,"passed_time":335.2831075,"remaining_time":0}
]}